README
setup.py
CLRS.egg-info/PKG-INFO
CLRS.egg-info/SOURCES.txt
CLRS.egg-info/dependency_links.txt
CLRS.egg-info/top_level.txt
sorting/__init__.py
sorting/bubble_sort.py
sorting/bucket_sort.py
sorting/counting_sort.py
sorting/heap_sort.py
sorting/insertion_sort.py
sorting/merge_sort.py
sorting/quick_sort.py
sorting/radix_sort.py
sorting/run_sample_input.py
sorting/selection_sort.py
sorting/test.py
tree/__init__.py
tree/binary_tree.py