Metadata-Version: 1.0
Name: CLRS
Version: 0.0.1
Summary: Algorithms from CLRS -- Introduction to Algorithms
Home-page: https://github.com/pc-zhang/CLRS.git
Author: Pengcheng Zhang
Author-email: zpc010@gmail.com
License: BSD
Keywords: algorithms
Platform: UNKNOWN
